indi_mr/__init__.py
indi_mr/d_to_m.py
indi_mr/d_to_r.py
indi_mr/fromindi.py
indi_mr/i_to_m.py
indi_mr/i_to_r.py
indi_mr/m_to_p.py
indi_mr/m_to_r.py
indi_mr/toindi.py
indi_mr/tools.py
indi_mr-0.4.0.dist-info/LICENSE
indi_mr-0.4.0.dist-info/METADATA
indi_mr-0.4.0.dist-info/WHEEL
indi_mr-0.4.0.dist-info/top_level.txt
indi_mr-0.4.0.dist-info/RECORD
