Metadata-Version: 2.1
Name: indi-mr
Version: 0.4.0
Summary: INDI - MQTT - REDIS - provides functions for transferring the INDI protocol via MQTT and converting to redis storage, with tools to read/write to redis and hence control remote instruments.
Home-page: https://github.com/bernie-skipole/indi-mr
Author: Bernard Czenkusz
Author-email: bernie@skipole.co.uk
License: UNKNOWN
Keywords: indi mqtt astronomy instrument
Platform: UNKNOWN
Classifier: Programming Language :: Python :: 3.9
Classifier: License :: OSI Approved :: MIT License
Classifier: Operating System :: POSIX :: Linux
Classifier: Topic :: Scientific/Engineering :: Astronomy
Classifier: Topic :: Scientific/Engineering :: Interface Engine/Protocol Translator
